{
  "project_info": {
    "project_number": "55112487274",
    "project_id": "edudashpro",
    "storage_bucket": "edudashpro.firebasestorage.app"
  },
  "client": [
    {
      "client_info": {
        "mobilesdk_app_id": "1:55112487274:android:31d82d314d44fbf8c49513",
        "android_client_info": {
          "package_name": "com.edudashpro"
        }
      },
      "oauth_client": [],
      "api_key": [
        {
          "current_key": "AIzaSyBcMcFWyTUZbptGtO89skTdiqTSFK7Wqw4"
        }
      ],
      "services": {
        "appinvite_service": {
          "other_platform_oauth_client": []
        }
      }
    },
    {
      "client_info": {
        "mobilesdk_app_id": "1:55112487274:android:364d1851971ea3a5c49513",
        "android_client_info": {
          "package_name": "com.edudashpro.app"
        }
      },
      "oauth_client": [],
      "api_key": [
        {
          "current_key": "AIzaSyBcMcFWyTUZbptGtO89skTdiqTSFK7Wqw4"
        }
      ],
      "services": {
        "appinvite_service": {
          "other_platform_oauth_client": []
        }
      }
    },
    {
      "client_info": {
        "mobilesdk_app_id": "1:55112487274:android:364d1851971ea3a5c49513",
        "android_client_info": {
          "package_name": "com.edudashpro.app.dev"
        }
      },
      "oauth_client": [],
      "api_key": [
        {
          "current_key": "AIzaSyBcMcFWyTUZbptGtO89skTdiqTSFK7Wqw4"
        }
      ],
      "services": {
        "appinvite_service": {
          "other_platform_oauth_client": []
        }
      }
    }
  ],
  "configuration_version": "1"
}
